{
  "genres": [
    {
      "genre": "Rock",
      "slug": "rock"
    },
    {
      "genre": "Punk",
      "slug": "punk"
    },
    {
      "genre": "R&B/Soul",
      "slug": "rbsoul"
    },
    {
      "genre": "Alternative",
      "slug": "alternative"
    },
    {
      "genre": "Jazz",
      "slug": "jazz"
    },
    {
      "genre": "Ambient",
      "slug": "ambient"
    },
    {
      "genre": "Europe",
      "slug": "europe"
    },
    {
      "genre": "Reggae",
      "slug": "reggae"
    },
    {
      "genre": "Cajun",
      "slug": "cajun"
    }
  ]
}
